docx_footer_extractor/__init__.py
docx_footer_extractor/extractor.py
docx_footer_extractor-1.0.0.dist-info/licenses/LICENSE
tests/__init__.py
tests/test_extractor.py
docx_footer_extractor-1.0.0.dist-info/METADATA
docx_footer_extractor-1.0.0.dist-info/WHEEL
docx_footer_extractor-1.0.0.dist-info/top_level.txt
docx_footer_extractor-1.0.0.dist-info/RECORD
