Metadata-Version: 2.4
Name: docx-footer-extractor
Version: 1.0.0
Summary: A Python library for extracting metadata from DOCX file footers using parallel processing
Home-page: https://github.com/sunilsmindspace/docx-footer-extractor
Author: Sunil K Sundaram
Author-email: Sunil K Sundaram <sunilsmindspace@gmail.com>
License: MIT
Project-URL: Homepage, https://github.com/sunilsmindspace/docx-footer-extractor
Project-URL: Bug Reports, https://github.com/sunilsmindspace/docx-footer-extractor/issues
Project-URL: Source, https://github.com/sunilsmindspace/docx-footer-extractor
Keywords: docx,metadata,footer,parallel,extraction,office,documents
Classifier: Development Status :: 4 - Beta
Classifier: Intended Audience :: Developers
Classifier: License :: OSI Approved :: MIT License
Classifier: Operating System :: OS Independent
Classifier: Programming Language :: Python :: 3
Classifier: Programming Language :: Python :: 3.9
Classifier: Programming Language :: Python :: 3.10
Classifier: Programming Language :: Python :: 3.11
Classifier: Programming Language :: Python :: 3.12
Classifier: Topic :: Office/Business :: Office Suites
Classifier: Topic :: Software Development :: Libraries :: Python Modules
Classifier: Topic :: Text Processing :: Markup
Requires-Python: >=3.9
License-File: LICENSE
Requires-Dist: python-docx>=0.8.11
Dynamic: author
Dynamic: home-page
Dynamic: license-file
Dynamic: requires-python
